{
  "version": "5",
  "dialect": "pg",
  "id": "a5265bbd-61ac-4d8d-96e7-310ebed9caca",
  "prevId": "00000000-0000-0000-0000-000000000000",
  "tables": {
    "group": {
      "name": "group",
      "schema": "",
      "columns": {
        "id": {
          "name": "id",
          "type": "serial",
          "primaryKey": true,
          "notNull": true
        },
        "portfolio_id": {
          "name": "portfolio_id",
          "type": "varchar(50)",
          "primaryKey": false,
          "notNull": true
        },
        "name": {
          "name": "name",
          "type": "varchar(128)",
          "primaryKey": false,
          "notNull": true
        },
        "description": {
          "name": "description",
          "type": "text",
          "primaryKey": false,
          "notNull": true
        },
        "created_at": {
          "name": "created_at",
          "type": "timestamp",
          "primaryKey": false,
          "notNull": true,
          "default": "now()"
        },
        "updated_at": {
          "name": "updated_at",
          "type": "timestamp",
          "primaryKey": false,
          "notNull": true,
          "default": "now()"
        }
      },
      "indexes": {},
      "foreignKeys": {},
      "compositePrimaryKeys": {},
      "uniqueConstraints": {}
    },
    "instance": {
      "name": "instance",
      "schema": "",
      "columns": {
        "id": {
          "name": "id",
          "type": "serial",
          "primaryKey": true,
          "notNull": true
        },
        "user_id": {
          "name": "user_id",
          "type": "integer",
          "primaryKey": false,
          "notNull": true
        },
        "logical_id": {
          "name": "logical_id",
          "type": "varchar(50)",
          "primaryKey": false,
          "notNull": false
        },
        "provision_token": {
          "name": "provision_token",
          "type": "varchar(50)",
          "primaryKey": false,
          "notNull": true
        },
        "name": {
          "name": "name",
          "type": "varchar(128)",
          "primaryKey": false,
          "notNull": true
        },
        "description": {
          "name": "description",
          "type": "text",
          "primaryKey": false,
          "notNull": true
        },
        "connection_type": {
          "name": "connection_type",
          "type": "instance_connection_type",
          "primaryKey": false,
          "notNull": false
        },
        "platform": {
          "name": "platform",
          "type": "varchar(100)",
          "primaryKey": false,
          "notNull": false
        },
        "distribution": {
          "name": "distribution",
          "type": "varchar(100)",
          "primaryKey": false,
          "notNull": false
        },
        "instance_type": {
          "name": "instance_type",
          "type": "varchar(50)",
          "primaryKey": false,
          "notNull": false
        },
        "cpu_cores": {
          "name": "cpu_cores",
          "type": "varchar(10)",
          "primaryKey": false,
          "notNull": false
        },
        "memory_in_gb": {
          "name": "memory_in_gb",
          "type": "varchar(10)",
          "primaryKey": false,
          "notNull": false
        },
        "storage_in_gb": {
          "name": "storage_in_gb",
          "type": "varchar(10)",
          "primaryKey": false,
          "notNull": false
        },
        "created_at": {
          "name": "created_at",
          "type": "timestamp",
          "primaryKey": false,
          "notNull": true,
          "default": "now()"
        },
        "updated_at": {
          "name": "updated_at",
          "type": "timestamp",
          "primaryKey": false,
          "notNull": true,
          "default": "now()"
        },
        "last_connection_at": {
          "name": "last_connection_at",
          "type": "timestamp",
          "primaryKey": false,
          "notNull": false
        }
      },
      "indexes": {},
      "foreignKeys": {
        "instance_user_id_user_id_fk": {
          "name": "instance_user_id_user_id_fk",
          "tableFrom": "instance",
          "tableTo": "user",
          "columnsFrom": [
            "user_id"
          ],
          "columnsTo": [
            "id"
          ],
          "onDelete": "no action",
          "onUpdate": "no action"
        }
      },
      "compositePrimaryKeys": {},
      "uniqueConstraints": {
        "instance_provision_token_unique": {
          "name": "instance_provision_token_unique",
          "nullsNotDistinct": false,
          "columns": [
            "provision_token"
          ]
        }
      }
    },
    "quota": {
      "name": "quota",
      "schema": "",
      "columns": {
        "id": {
          "name": "id",
          "type": "serial",
          "primaryKey": true,
          "notNull": true
        },
        "user_id": {
          "name": "user_id",
          "type": "integer",
          "primaryKey": false,
          "notNull": true
        },
        "max_instances": {
          "name": "max_instances",
          "type": "integer",
          "primaryKey": false,
          "notNull": true,
          "default": 2
        }
      },
      "indexes": {},
      "foreignKeys": {
        "quota_user_id_user_id_fk": {
          "name": "quota_user_id_user_id_fk",
          "tableFrom": "quota",
          "tableTo": "user",
          "columnsFrom": [
            "user_id"
          ],
          "columnsTo": [
            "id"
          ],
          "onDelete": "no action",
          "onUpdate": "no action"
        }
      },
      "compositePrimaryKeys": {},
      "uniqueConstraints": {}
    },
    "user": {
      "name": "user",
      "schema": "",
      "columns": {
        "id": {
          "name": "id",
          "type": "serial",
          "primaryKey": true,
          "notNull": true
        },
        "username": {
          "name": "username",
          "type": "varchar(128)",
          "primaryKey": false,
          "notNull": true
        },
        "role": {
          "name": "role",
          "type": "user_role",
          "primaryKey": false,
          "notNull": true
        },
        "created_at": {
          "name": "created_at",
          "type": "timestamp",
          "primaryKey": false,
          "notNull": true,
          "default": "now()"
        },
        "updated_at": {
          "name": "updated_at",
          "type": "timestamp",
          "primaryKey": false,
          "notNull": true,
          "default": "now()"
        },
        "last_login_at": {
          "name": "last_login_at",
          "type": "timestamp",
          "primaryKey": false,
          "notNull": false
        }
      },
      "indexes": {},
      "foreignKeys": {},
      "compositePrimaryKeys": {},
      "uniqueConstraints": {
        "user_username_unique": {
          "name": "user_username_unique",
          "nullsNotDistinct": false,
          "columns": [
            "username"
          ]
        }
      }
    },
    "user_to_group": {
      "name": "user_to_group",
      "schema": "",
      "columns": {
        "user_id": {
          "name": "user_id",
          "type": "integer",
          "primaryKey": false,
          "notNull": true
        },
        "group_id": {
          "name": "group_id",
          "type": "integer",
          "primaryKey": false,
          "notNull": true
        }
      },
      "indexes": {},
      "foreignKeys": {
        "user_to_group_user_id_user_id_fk": {
          "name": "user_to_group_user_id_user_id_fk",
          "tableFrom": "user_to_group",
          "tableTo": "user",
          "columnsFrom": [
            "user_id"
          ],
          "columnsTo": [
            "id"
          ],
          "onDelete": "no action",
          "onUpdate": "no action"
        },
        "user_to_group_group_id_group_id_fk": {
          "name": "user_to_group_group_id_group_id_fk",
          "tableFrom": "user_to_group",
          "tableTo": "group",
          "columnsFrom": [
            "group_id"
          ],
          "columnsTo": [
            "id"
          ],
          "onDelete": "no action",
          "onUpdate": "no action"
        }
      },
      "compositePrimaryKeys": {
        "user_to_group_user_id_group_id": {
          "name": "user_to_group_user_id_group_id",
          "columns": [
            "user_id",
            "group_id"
          ]
        }
      },
      "uniqueConstraints": {}
    }
  },
  "enums": {
    "instance_connection_type": {
      "name": "instance_connection_type",
      "values": {
        "VNC": "VNC",
        "RDP": "RDP"
      }
    },
    "user_role": {
      "name": "user_role",
      "values": {
        "NONE": "NONE",
        "PENDING": "PENDING",
        "USER": "USER",
        "ADMIN": "ADMIN"
      }
    }
  },
  "schemas": {},
  "_meta": {
    "schemas": {},
    "tables": {},
    "columns": {}
  }
}